dynamic_valuation/__init__.py
dynamic_valuation/bounded_ivp.py
dynamic_valuation/crunch.py
dynamic_valuation/de.py
dynamic_valuation/fun - Copy.py
dynamic_valuation/fun.py
dynamic_valuation/hc_vfi.py
dynamic_valuation/resource_stocks.py
dynamic_valuation/series_approx.py
dynamic_valuation/time_method.py
dynamic_valuation/vfi.py
dynamic_valuation-2.dist-info/METADATA
dynamic_valuation-2.dist-info/WHEEL
dynamic_valuation-2.dist-info/top_level.txt
dynamic_valuation-2.dist-info/RECORD
