Metadata-Version: 2.1
Name: dynamic_valuation
Version: 2
Summary: Find the present value of a capital asset stocks and/or    flows subject to an equation of motion.
Author: Eric Larson
Author-email: ericl3@illinois.edu
Requires-Dist: numpy
Requires-Dist: matplotlib
Requires-Dist: scipy
Requires-Dist: pandas
